face_authentication_lib/__init__.py
face_authentication_lib/exceptions.py
face_authentication_lib/face_auth.py
face_authentication_lib-0.2.1.data/scripts/face_auth
face_authentication_lib-0.2.1.dist-info/LICENSE.txt
face_authentication_lib-0.2.1.dist-info/METADATA
face_authentication_lib-0.2.1.dist-info/WHEEL
face_authentication_lib-0.2.1.dist-info/top_level.txt
face_authentication_lib-0.2.1.dist-info/RECORD
