Metadata-Version: 2.1
Name: face-authentication-lib
Version: 0.2.1
Summary: Setting up a python face authentication package
Home-page: UNKNOWN
Author: SamanAI
Author-email: info@saman.ai
License: MIT
Keywords: AI,face authentication,face detection
Platform: UNKNOWN
Classifier: Intended Audience :: Developers
Classifier: License :: OSI Approved :: MIT License
Classifier: Programming Language :: Python :: 3
Classifier: Operating System :: OS Independent
License-File: LICENSE.txt
Requires-Dist: requests (==2.20.0)
